Workbook

Sheet Transactions
A1: Transactions_ID | B1: Date | C1: Country | D1: Currency | E1: Type | F1: Category | G1: Amount | H1: Account | I1: Status
A2: TXN001 | B2: 46025 | C2: India | D2: USD | E2: Inflow | F2: Funding | G2: 25000 | H2: Main Account | I2: Completed
A3: TXN002 | B3: 46027 | C3: Kenya | D3: USD | E3: Outflow | F3: Operations | G3: 8500 | H3: Main Account | I3: Completed
A4: TXN003 | B4: 46030 | C4: Germany | D4: EUR | E4: Inflow | F4: Funding | G4: 18000 | H4: Reserve Account | I4: Completed
A5: TXN004 | B5: 46034 | C5: India | D5: USD | E5: Outflow | F5: Technology | G5: 4200 | H5: Main Account | I5: Completed
A6: TXN005 | B6: 46037 | C6: Ethiopia | D6: USD | E6: Outflow | F6: Logistics | G6: 12500 | H6: Operations Account | I6: Completed
A7: TXN006 | B7: 46040 | C7: France | D7: EUR | E7: Inflow | F7: Funding | G7: 22000 | H7: Reserve Account | I7: Completed
A8: TXN007 | B8: 46044 | C8: India | D8: USD | E8: Outflow | F8: Administration | G8: 3800 | H8: Main Account | I8: Pending
A9: TXN008 | B9: 46049 | C9: Kenya | D9: USD | E9: Outflow | F9: Salaries | G9: 14500 | H9: Operations Account | I9: Completed
A10: TXN009 | B10: 46055 | C10: India | D10: USD | E10: Inflow | F10: Funding | G10: 30000 | H10: Main Account | I10: Completed
A11: TXN010 | B11: 46058 | C11: Bangladesh | D11: USD | E11: Outflow | F11: Emergency Response | G11: 19000 | H11: Operations Account | I11: Completed
A12: TXN011 | B12: 46062 | C12: Germany | D12: EUR | E12: Outflow | F12: Technology | G12: 7200 | H12: Reserve Account | I12: Completed
A13: TXN012 | B13: 46066 | C13: Ethiopia | D13: USD | E13: Outflow | F13: Logistics | G13: 16800 | H13: Operations Account | I13: Completed
... A66: TXN065 | B66: 46293 | C66: France | D66: EUR | E66: Inflow | F66: Funding | G66: 41000 | H66: Reserve Account | I66: Comp

Sheet Budget
A1: Month | B1: Category | C1: Budget
A2: 46048 | B2: Operations | C2: 20000
A3: 46048 | B3: Technology | C3: 10000
A4: 46048 | B4: Logistics | C4: 30000
A5: 46048 | B5: Administration | C5: 12000
A6: 46048 | B6: Salaries | C6: 18000
A7: 46048 | B7: Emergency Response | C7: 25000
A8: 46079 | B8: Operations | C8: 22000
A9: 46079 | B9: Technology | C9: 10000
A10: 46079 | B10: Logistics | C10: 30000
A11: 46079 | B11: Administration | C11: 12000
A12: 46079 | B12: Salaries | C12: 19000
A13: 46079 | B13: Emergency Response | C13: 30000
... A73: 46382 | B73: Emergency Response | C73: 55000

Sheet Dashboard
A1: TREASURY & FINANCIAL ANALYSIS DASHBOARD
A3: TOTAL INFLOW | D3: TOTAL OUTFLOW | G3: NET CASH FLOW | J3: TRANSACTIONS
A4: =SUMIF(Transactions!E:E,"INFLOW",Transactions!G:G) -> 710500 | D4: =SUMIF(Transactions!E:E,"OUTFLOW",Transactions!G:G) -> 655400 | G4: =A4-D4 -> 55100 | J4: =COUNTA(Transactions!A:A)-1 -> 65
A6: PENDING TRANSACTIONS
A7: 6
A10: Month | B10: Inflow | C10: Outflow | D10: Net Cash Flow | F10: ACCOUNT ANALYSIS
A11: 46048 | B11: =SUMIFS(Transactions!G:G,Transactions!E:E,"Inflow",Transactions!B:B,">="&DATE(2026,1,1),Transactions!B:B,"<"&DATE(2026,2,1)) -> 65000 | C11: =SUMIFS(Transactions!G:G,Transactions!E:E,"Outflow",Transactions!B:B,">="&DATE(2026,1,1),Transactions!B:B,"<"&DATE(2026,2,1)) -> 43500 | D11: =B11-C11 -> 21500 | F11: ACCOUNT ANALYSIS | G11: INFLOW | H11: OUTFLOW
A12: 46079 | B12: =SUMIFS(Transactions!G:G,Transactions!E:E,"Inflow",Transactions!B:B,">="&DATE(2026,2,1),Transactions!B:B,"<"&DATE(2026,3,1)) -> 57500 | C12: =SUMIFS(Transactions!G:G,Transactions!E:E,"Outflow",Transactions!B:B,">="&DATE(2026,2,1),Transactions!B:B,"<"&DATE(2026,3,1)) -> 56700 | D12: =B12-C12 -> 800 | F12: Main Account | G12: =SUMIFS(Transactions!G:G,Transactions!H:H,F12,Transactions!E:E,"Inflow") -> 312000 | H12: =SUMIFS(Transactions!G:G,Transactions!H:H,F12,Transactions!E:E,"Outflow") -> 111200
A13: 46107 | B13: =SUMIFS(Transactions!G:G,Transactions!E:E,"Inflow",Transactions!B:B,">="&DATE(2026,3,1),Transactions!B:B,"<"&DATE(2026,4,1)) -> 55000 | C13: =SUMIFS(Transactions!G:G,Transactions!E:E,"Outflow",Transactions!B:B,">="&DATE(2026,3,1),Transactions!B:B,"<"&DATE(2026,4,1)) -> 69000 | D13: =B13-C13 -> -14000 | F13: Reserve Account | G13: =SUMIFS(Transactions!G:G,Transactions!H:H,F13,Transactions!E:E,"Inflow") -> 398500 | H13: =SUMIFS(Transactions!G:G,Transactions!H:H,F13,Transactions!E:E,"Outflow") -> 66200
A14: 46138 | B14: =SUMIFS(Transactions!G:G,Transactions!E:E,"Inflow",Transactions!B:B,">="&DATE(2026,4,1),Transactions!B:B,"<"&DATE(2026,5,1)) -> 100000 | C14: =SUMIFS(Transactions!G:G,Transactions!E:E,"Inflow",Transactions!B:B,">="&DATE(2026,4,1),Transactions!B:B,"<"&DATE(2026,5,1)) -> 100000 | D14: =B14-C14 -> 0 | F14: Operations Account | G14: =SUMIFS(Transactions!G:G,Transactions!H:H,F14,Transactions!E:E,"Inflow") -> 0 | H14: =SUMIFS(Transactions!G:G,Transactions!H:H,F14,Transactions!E:E,"Outflow") -> 478000
A15: 46168 | B15: =SUMIFS(Transactions!G:G,Transactions!E:E,"Inflow",Transactions!B:B,">="&DATE(2026,5,1),Transactions!B:B,"<"&DATE(2026,6,1)) -> 61000 | C15: =SUMIFS(Transactions!G:G,Transactions!E:E,"Outflow",Transactions!B:B,">="&DATE(2026,5,1),Transactions!B:B,"<"&DATE(2026,6,1)) -> 74200 | D15: =B15-C15 -> -13200
A16: 46199 | B16: =SUMIFS(Transactions!G:G,Transactions!E:E,"Inflow",Transactions!B:B,">="&DATE(2026,6,1),Transactions!B:B,"<"&DATE(2026,7,1)) -> 96000 | C16: =SUMIFS(Transactions!G:G,Transactions!E:E,"Outflow",Transactions!B:B,">="&DATE(2026,6,1),Transactions!B:B,"<"&DATE(2026,7,1)) -> 72100 | D16: =B16-C16 -> 23900
A17: 46229 | B17: =SUMIFS(Transactions!G:G,Transactions!E:E,"Inflow",Transactions!B:B,">="&DATE(2026,7,1),Transactions!B:B,"<"&DATE(2026,8,1)) -> 87000 | C17: =SUMIFS(Transactions!G:G,Transactions!E:E,"Outflow",Transactions!B:B,">="&DATE(2026,7,1),Transactions!B:B,"<"&DATE(2026,8,1)) -> 92700 | D17: =B17-C17 -> -5700
A18: 46260 | B18: =SUMIFS(Transactions!G:G,Transactions!E:E,"Inflow",Transactions!B:B,">="&DATE(2026,8,1),Transactions!B:B,"<"&DATE(2026,9,1)) -> 75000 | C18: =SUMIFS(Transactions!G:G,Transactions!E:E,"Outflow",Transactions!B:B,">="&DATE(2026,8,1),Transactions!B:B,"<"&DATE(2026,9,1)) -> 84900 | D18: =B18-C18 -> -9900
A19: 46291 | B19: =SUMIFS(Transactions!G:G,Transactions!E:E,"Inflow",Transactions!B:B,">="&DATE(2026,9,1),Transactions!B:B,"<"&DATE(2026,10,1)) -> 114000 | C19: =SUMIFS(Transactions!G:G,Transactions!E:E,"Outflow",Transactions!B:B,">="&DATE(2026,9,1),Transactions!B:B,"<"&DATE(2026,10,1)) -> 87900 | D19: =B19-C19 -> 26100
A31: BUDGET VS ACTUAL ANALYSIS | F31: PENDING TRANSACTIONS
A32: CATEGORY | B32: BUDGET | C32: ACTUAL | D32: VARIANCE | F32: PENDING COUNT | G32: AMOUNT
A33: Operations | B33: =SUMIF(Budget!B:B,A33,Budget!C:C) -> 317000 | C33: =SUMIF(Transactions!F:F,A33,Transactions!G:G) -> 63300 | D33: =B33-C33 -> 253700 | F33: =COUNTIF(Transactions!I:I,"Pending") -> 6 | G33: =SUMIF(Transactions!I:I,"Pending",Transactions!G:G) -> 59600
A34: Technology | B34: =SUMIF(Budget!B:B,A34,Budget!C:C) -> 175000 | C34: =SUMIF(Transactions!F:F,A34,Transactions!G:G) -> 70700 | D34: =B34-C34 -> 104300
A35: Logistics | B35: =SUMIF(Budget!B:B,A35,Budget!C:C) -> 465000 | C35: =SUMIF(Transactions!F:F,A35,Transactions!G:G) -> 191800 | D35: =B35-C35 -> 273200
A36: Administration | B36: =SUMIF(Budget!B:B,A36,Budget!C:C) -> 183000 | C36: =SUMIF(Transactions!F:F,A36,Transactions!G:G) -> 18100 | D36: =B36-C36 -> 164900
A37: Salaries | B37: =SUMIF(Budget!B:B,A37,Budget!C:C) -> 273000 | C37: =SUMIF(Transactions!F:F,A37,Transactions!G:G) -> 97000 | D37: =B37-C37 -> 176000
A38: Emergency Response | B38: =SUMIF(Budget!B:B,A38,Budget!C:C) -> 495000 | C38: =SUMIF(Transactions!F:F,A38,Transactions!G:G) -> 210000 | D38: =B38-C38 -> 285000
